scripts.py
helloworld_v1-0.1.dist-info/METADATA
helloworld_v1-0.1.dist-info/WHEEL
helloworld_v1-0.1.dist-info/top_level.txt
helloworld_v1-0.1.dist-info/RECORD
