Metadata-Version: 2.1
Name: helloworld-v1
Version: 0.1
Summary: Say hello!
Home-page: UNKNOWN
Author: UNKNOWN
Author-email: UNKNOWN
License: UNKNOWN
Platform: UNKNOWN
